oapi3/__init__.py
oapi3/client.py
oapi3/entities/__init__.py
oapi3/entities/base.py
oapi3/entities/media_types.py
oapi3/entities/operations.py
oapi3/entities/parameters.py
oapi3/entities/paths.py
oapi3/entities/schema.py
oapi3/exceptions.py
oapi3/jsonschema_validator.py
oapi3/resolve.py
oapi3/schema.py
oapi3-1.5.3.dist-info/LICENSE
oapi3-1.5.3.dist-info/METADATA
oapi3-1.5.3.dist-info/WHEEL
oapi3-1.5.3.dist-info/RECORD
