Metadata-Version: 2.3
Name: oapi3
Version: 1.5.3
Summary: Validator of openapi3 requests and responses
Author: Mayorov Evgeny
Author-email: motormen@gmail.com
Requires-Python: >=3.7.3
Classifier: Programming Language :: Python :: 3
Classifier: Programming Language :: Python :: 3.8
Classifier: Programming Language :: Python :: 3.9
Classifier: Programming Language :: Python :: 3.10
Classifier: Programming Language :: Python :: 3.11
Classifier: Programming Language :: Python :: 3.12
Classifier: Programming Language :: Python :: 3.13
Requires-Dist: jsonschema (==4.17.3)
Requires-Dist: pyyaml (==6.0.1)
